pyGMs/__init__.py
pyGMs/_profile.py
pyGMs/_rbm.py
pyGMs/causal.py
pyGMs/csp.py
pyGMs/decisions.py
pyGMs/draw.py
pyGMs/factor.py
pyGMs/factorGauss.py
pyGMs/factorSparse.py
pyGMs/filetypes.py
pyGMs/graphmodel.py
pyGMs/indexedheap.py
pyGMs/ising.py
pyGMs/jupyter.py
pyGMs/learning.py
pyGMs/messagepass.py
pyGMs/misc.py
pyGMs/montecarlo.py
pyGMs/regiongraph.py
pyGMs/search.py
pyGMs/search1.py
pyGMs/search2.py
pyGMs/search_sum.py
pyGMs/varset_py.py
pyGMs/varset_py2.py
pyGMs/weighted.py
pyGMs/wmb.py
pyGMs/wogm.py
pyGMs/data/__init__.py
pyGMs/data/catalog.py
pyGMs/data/sources.json
pygms-0.3.4.dist-info/METADATA
pygms-0.3.4.dist-info/WHEEL
pygms-0.3.4.dist-info/top_level.txt
pygms-0.3.4.dist-info/RECORD
