Metadata-Version: 2.4
Name: pyGMs
Version: 0.3.4
Summary: Python Graphical Models Toolbox
Author: Alexander Ihler
Author-email: ihler@ics.uci.edu
Classifier: Programming Language :: Python :: 3
Classifier: License :: OSI Approved :: BSD License
Classifier: Operating System :: OS Independent
Requires-Python: >=3.6
Dynamic: author
Dynamic: author-email
Dynamic: classifier
Dynamic: description
Dynamic: description-content-type
Dynamic: requires-python
Dynamic: summary
